pyeventcloud/__init__.py
pyeventcloud/bindings/__init__.py
pyeventcloud/bindings/http.py
pyeventcloud/bindings/kafka.py
pyeventcloud/core/__init__.py
pyeventcloud/core/event.py
pyeventcloud/core/exceptions.py
pyeventcloud/extensions/__init__.py
pyeventcloud/extensions/partitionkey.py
pyeventcloud/extensions/registry.py
pyeventcloud/formats/__init__.py
pyeventcloud/formats/json.py
pyeventcloud/py.typed
pyeventcloud/specs/__init__.py
pyeventcloud/specs/spec_v10.py
pyeventcloud/utils/__init__.py
pyeventcloud/utils/types.py
pyeventcloud/validation/__init__.py
pyeventcloud/validation/validators.py
pyeventcloud-0.1.0.dist-info/WHEEL
pyeventcloud-0.1.0.dist-info/METADATA
pyeventcloud-0.1.0.dist-info/RECORD
