Metadata-Version: 2.3
Name: pyeventcloud
Version: 0.1.0
Summary: CloudEvents SDK for Python with zero dependencies and complete protocol bindings
Keywords: cloudevents,events,sdk,kafka,http,eventing,cloud-native,serverless
Author: Tudor Plugaru
Author-email: Tudor Plugaru <tudor@plugaru.me>
License: Apache-2.0
Classifier: Development Status :: 4 - Beta
Classifier: Intended Audience :: Developers
Classifier: License :: OSI Approved :: Apache Software License
Classifier: Operating System :: OS Independent
Classifier: Programming Language :: Python :: 3
Classifier: Programming Language :: Python :: 3.11
Classifier: Programming Language :: Python :: 3.12
Classifier: Programming Language :: Python :: 3.13
Classifier: Programming Language :: Python :: 3.14
Classifier: Programming Language :: Python :: 3 :: Only
Classifier: Topic :: Software Development :: Libraries :: Python Modules
Classifier: Topic :: System :: Distributed Computing
Classifier: Typing :: Typed
Requires-Python: >=3.11
Project-URL: Documentation, https://github.com/plugarut/pyeventcloud#readme
Project-URL: Homepage, https://github.com/plugarut/pyeventcloud
Project-URL: Issues, https://github.com/plugarut/pyeventcloud/issues
Project-URL: Repository, https://github.com/plugarut/pyeventcloud
